markdown_table_repair/__init__.py
markdown_table_repair/repair.py
markdown_table_repair-0.1.0.dist-info/LICENSE
markdown_table_repair-0.1.0.dist-info/METADATA
markdown_table_repair-0.1.0.dist-info/WHEEL
markdown_table_repair-0.1.0.dist-info/top_level.txt
markdown_table_repair-0.1.0.dist-info/RECORD
