Metadata-Version: 2.1
Name: markdown-table-repair
Version: 0.1.0
Summary: A package to repair and clean malformed markdown tables.
Home-page: https://github.com/MAbdanM/markdown-table-repair
Author: Muhammad Abdan Mulia
Author-email: abdanmulia@gmail.com
Classifier: Programming Language :: Python :: 3
Classifier: License :: OSI Approved :: MIT License
License-File: LICENSE
Requires-Dist: pandas
